kurl/__init__.py
kurl/__main__.py
kurl/hooking/__init__.py
kurl/hooking/ante_build_hook.py
kurl/hooking/ante_release_hook.py
kurl/hooking/post_build_hook.py
kurl/hooking/post_release_hook.py
kurl/pyrustic_data/hooking.json
kurl/pyrustic_data/hubstore.json
kurl/pyrustic_data/release_info.json
kurl/pyrustic_data/backstage/config/build.json
kurl/pyrustic_data/backstage/config/init.json
kurl/pyrustic_data/backstage/config/release.json
kurl/pyrustic_data/backstage/data/build_report.json
kurl/pyrustic_data/backstage/data/github_release_form.json
kurl/pyrustic_data/backstage/hooking/build.json
kurl/pyrustic_data/backstage/hooking/init.json
kurl/pyrustic_data/backstage/hooking/release.json
kurl/pyrustic_data/backstage/report/build_report.json
kurl/pyrustic_data/backstage/report/release_report.json
kurl/pyrustic_data/hubstore/img.json
kurl/pyrustic_data/hubstore/promotion.json
secret/SCRATCH.py
secret/__init__.py
tests/__init__.py
tests/__main__.py
kurl-0.0.6.dist-info/LICENSE
kurl-0.0.6.dist-info/METADATA
kurl-0.0.6.dist-info/WHEEL
kurl-0.0.6.dist-info/entry_points.txt
kurl-0.0.6.dist-info/top_level.txt
kurl-0.0.6.dist-info/RECORD
